marzban_api_client/__init__.py
marzban_api_client/api/__init__.py
marzban_api_client/api/admin/__init__.py
marzban_api_client/api/admin/admin_token.py
marzban_api_client/api/admin/create_admin.py
marzban_api_client/api/admin/get_admins.py
marzban_api_client/api/admin/get_current_admin.py
marzban_api_client/api/admin/modify_admin.py
marzban_api_client/api/admin/remove_admin.py
marzban_api_client/api/core/__init__.py
marzban_api_client/api/core/get_core_config.py
marzban_api_client/api/core/get_core_stats.py
marzban_api_client/api/core/modify_core_config.py
marzban_api_client/api/core/restart_core.py
marzban_api_client/api/default/__init__.py
marzban_api_client/api/default/base.py
marzban_api_client/api/node/__init__.py
marzban_api_client/api/node/add_node.py
marzban_api_client/api/node/get_node.py
marzban_api_client/api/node/get_node_settings.py
marzban_api_client/api/node/get_nodes.py
marzban_api_client/api/node/get_usage.py
marzban_api_client/api/node/modify_node.py
marzban_api_client/api/node/reconnect_node.py
marzban_api_client/api/node/remove_node.py
marzban_api_client/api/subscription/__init__.py
marzban_api_client/api/subscription/user_get_usage.py
marzban_api_client/api/subscription/user_subscription.py
marzban_api_client/api/subscription/user_subscription_info.py
marzban_api_client/api/subscription/user_subscription_with_client_type.py
marzban_api_client/api/system/__init__.py
marzban_api_client/api/system/get_hosts.py
marzban_api_client/api/system/get_inbounds.py
marzban_api_client/api/system/get_system_stats.py
marzban_api_client/api/system/modify_hosts.py
marzban_api_client/api/user/__init__.py
marzban_api_client/api/user/add_user.py
marzban_api_client/api/user/delete_expired_users.py
marzban_api_client/api/user/get_expired_users.py
marzban_api_client/api/user/get_user.py
marzban_api_client/api/user/get_user_usage.py
marzban_api_client/api/user/get_users.py
marzban_api_client/api/user/modify_user.py
marzban_api_client/api/user/remove_user.py
marzban_api_client-0.4.9.dist-info/LICENSE
marzban_api_client-0.4.9.dist-info/METADATA
marzban_api_client-0.4.9.dist-info/WHEEL
marzban_api_client-0.4.9.dist-info/RECORD
