Metadata-Version: 2.1
Name: marzban-api-client
Version: 0.4.9
Summary: A client library for accessing MarzbanAPI
Home-page: https://github.com/oXIIIo/marzban-api-client
License: MIT
Author: XIII
Requires-Python: >=3.8,<4.0
Classifier: License :: OSI Approved :: MIT License
Classifier: Programming Language :: Python :: 3
Classifier: Programming Language :: Python :: 3.8
Classifier: Programming Language :: Python :: 3.9
Classifier: Programming Language :: Python :: 3.10
Classifier: Programming Language :: Python :: 3.11
Classifier: Programming Language :: Python :: 3.12
Requires-Dist: attrs (>=21.3.0)
Requires-Dist: httpx (>=0.20.0,<0.26.0)
Requires-Dist: python-dateutil (>=2.8.0,<3.0.0)
Project-URL: Repository, https://github.com/oXIIIo/marzban-api-client
